<?xml version="1.0" ?>
<SmellBaseline>
  <ManuallySuppressedIssues/>
  <CurrentIssues>
    <ID>LongParameterList:PlayingNowScreen.kt$( state: MoviesState = MoviesState(), showNoInternetDialog: Boolean = false, showErrorDialog: Boolean = false, onNetworkErrorDismiss: () -&gt; Unit = {}, onErrorDismiss: () -&gt; Unit = {}, sendEvent: (MovieEvent) -&gt; Unit )</ID>
    <ID>LongParameterList:PopularMoviesScreen.kt$( state: MoviesState = MoviesState(), sendEvent: (MovieEvent) -&gt; Unit = {}, showNoInternetDialog: Boolean = false, showErrorDialog: Boolean = false, onNetworkErrorDismiss: () -&gt; Unit = {}, onErrorDismiss: () -&gt; Unit = {}, onMovieClicked: (id: Int) -&gt; Unit = {} )</ID>
    <ID>MagicNumber:KotlinAndroid.kt$27</ID>
    <ID>MagicNumber:KotlinAndroid.kt$35</ID>
    <ID>MaxLineLength:ApiTest.kt$ApiTest.Companion$overview = """A botched store robbery places Wonder Woman in a global battle against a powerful and mysterious ancient force that puts her powers in jeopardy."""</ID>
    <ID>MaxLineLength:PopularMoviesViewModelTest.kt$PopularMoviesViewModelTest$fun</ID>
    <ID>UnusedParameter:CoreModule.kt$CoreModule$app: Application</ID>
    <ID>UnusedParameter:KotlinAndroid.kt$project: Project</ID>
  </CurrentIssues>
</SmellBaseline>
